mcp_feedback_enhanced/__init__.py
mcp_feedback_enhanced/__main__.py
mcp_feedback_enhanced/debug.py
mcp_feedback_enhanced/i18n.py
mcp_feedback_enhanced/server.py
mcp_feedback_enhanced/test_mcp_enhanced.py
mcp_feedback_enhanced/test_qt_gui.py
mcp_feedback_enhanced/test_web_ui.py
mcp_feedback_enhanced/gui/__init__.py
mcp_feedback_enhanced/gui/main.py
mcp_feedback_enhanced/gui/locales/README.md
mcp_feedback_enhanced/gui/locales/en/translations.json
mcp_feedback_enhanced/gui/locales/zh-CN/translations.json
mcp_feedback_enhanced/gui/locales/zh-TW/translations.json
mcp_feedback_enhanced/gui/models/__init__.py
mcp_feedback_enhanced/gui/models/feedback.py
mcp_feedback_enhanced/gui/styles/__init__.py
mcp_feedback_enhanced/gui/styles/themes.py
mcp_feedback_enhanced/gui/tabs/__init__.py
mcp_feedback_enhanced/gui/tabs/about_tab.py
mcp_feedback_enhanced/gui/tabs/command_tab.py
mcp_feedback_enhanced/gui/tabs/feedback_tab.py
mcp_feedback_enhanced/gui/tabs/settings_tab.py
mcp_feedback_enhanced/gui/tabs/summary_tab.py
mcp_feedback_enhanced/gui/utils/__init__.py
mcp_feedback_enhanced/gui/utils/shortcuts.py
mcp_feedback_enhanced/gui/utils/utils.py
mcp_feedback_enhanced/gui/widgets/__init__.py
mcp_feedback_enhanced/gui/widgets/image_preview.py
mcp_feedback_enhanced/gui/widgets/image_upload.py
mcp_feedback_enhanced/gui/widgets/styled_spinbox.py
mcp_feedback_enhanced/gui/widgets/switch.py
mcp_feedback_enhanced/gui/widgets/text_edit.py
mcp_feedback_enhanced/gui/widgets/timeout_widget.py
mcp_feedback_enhanced/gui/window/__init__.py
mcp_feedback_enhanced/gui/window/command_executor.py
mcp_feedback_enhanced/gui/window/config_manager.py
mcp_feedback_enhanced/gui/window/feedback_window.py
mcp_feedback_enhanced/gui/window/tab_manager.py
mcp_feedback_enhanced/testing/__init__.py
mcp_feedback_enhanced/testing/config.py
mcp_feedback_enhanced/testing/mcp_client.py
mcp_feedback_enhanced/testing/reporter.py
mcp_feedback_enhanced/testing/scenarios.py
mcp_feedback_enhanced/testing/utils.py
mcp_tingquan-2.2.5.dist-info/METADATA
mcp_tingquan-2.2.5.dist-info/WHEEL
mcp_tingquan-2.2.5.dist-info/entry_points.txt
mcp_tingquan-2.2.5.dist-info/licenses/LICENSE
mcp_tingquan-2.2.5.dist-info/RECORD
