Metadata-Version: 2.4
Name: mcp-tingquan
Version: 2.2.5
Summary: Enhanced MCP server for interactive user feedback and command execution in AI-assisted development, featuring dual UI support (Qt GUI and Web UI) with intelligent environment detection.
Project-URL: Homepage, https://github.com/maticarmy/mcp-tingquan
Project-URL: Repository, https://github.com/maticarmy/mcp-tingquan
Project-URL: Issues, https://github.com/maticarmy/mcp-tingquan/issues
Author-email: Minidoracat <minidora0702@gmail.com>
License-File: LICENSE
Keywords: ai,development,feedback,gui,interactive,mcp,web-ui
Classifier: Development Status :: 4 - Beta
Classifier: Intended Audience :: Developers
Classifier: License :: OSI Approved :: MIT License
Classifier: Programming Language :: Python :: 3
Classifier: Programming Language :: Python :: 3.11
Classifier: Programming Language :: Python :: 3.12
Classifier: Topic :: Software Development :: Libraries :: Python Modules
Classifier: Topic :: Software Development :: User Interfaces
Requires-Python: >=3.11
Requires-Dist: aiohttp>=3.8.0
Requires-Dist: fastapi>=0.115.0
Requires-Dist: fastmcp>=2.0.0
Requires-Dist: jinja2>=3.1.0
Requires-Dist: psutil>=7.0.0
Requires-Dist: pyside6>=6.8.2.1
Requires-Dist: uvicorn>=0.30.0
Requires-Dist: websockets>=13.0.0
Provides-Extra: dev
Requires-Dist: pytest-asyncio>=0.21.0; extra == 'dev'
Requires-Dist: pytest>=7.0.0; extra == 'dev'
